{
  "id": "3",
  "video_overlay": {
    "bottom": {
      "components": [
        {
          "type": "title",
          "label": "Spawn rebels with the button"
        }
      ]
    },
    "left": {
      "components": [
        {
          "type": "button",
          "name": "action-rebel",
          "label": "Spawn rebel",
          "style": {
            "background": "url('https://rpg-companion.vercel.app/static/media/button.ab516115.png') center / 100% 100% no-repeat padding-box"
          },
          "extension": {
            "title": {
              "label": "Spawn a REBEL"
            },
            "submit": {
              "label": "Send"
            },
            "components": [
              {
                "type": "image",
                "name": "img1",
                "src": "http://jm.cartlamy.com/css/images/myprevimeteo.png",
                "style": {
                  "maxHeight": "125px"
                }
              },
              {
                "type": "input",
                "name": "ext-teaser-quote",
                "label": "Punchline",
                "placeholder": "Write here"
              }
            ]
          },
          "cooldown": {
            "duration": 20000,
            "broadcast": false
          }
        },
        {
          "type": "image",
          "name": "img1",
          "src": "https://rpg-companion.vercel.app/static/media/border-image.29ef5ac8.png"
        }
      ]
    }
  }
}
